seven_cdp/__init__.py
seven_cdp/libs/__init__.py
seven_cdp/libs/customize/__init__.py
seven_cdp/libs/customize/asset_base_model.py
seven_cdp/libs/customize/cdp_helper.py
seven_cdp/models/__init__.py
seven_cdp-1.0.1.dist-info/LICENSE
seven_cdp-1.0.1.dist-info/METADATA
seven_cdp-1.0.1.dist-info/WHEEL
seven_cdp-1.0.1.dist-info/top_level.txt
seven_cdp-1.0.1.dist-info/RECORD
