Metadata-Version: 2.1
Name: seven-cdp
Version: 1.0.1
Summary: seven cdp
Home-page: http://gitlab.tdtech.gao7.com/newfire/hk_cap/hk_cdp/server/seven_cdp.git
Author: seven
Author-email: tech@gao7.com
License: MIT
Platform: UNKNOWN
Classifier: Topic :: Software Development :: Libraries :: Python Modules
Classifier: Programming Language :: Python
Classifier: Programming Language :: Python :: 3.4
Classifier: Programming Language :: Python :: 3.5
Classifier: Programming Language :: Python :: 3.5
Classifier: Programming Language :: Python :: 3.6
Classifier: Programming Language :: Python :: 3.7
Classifier: Programming Language :: Python :: 3.8
Classifier: Programming Language :: Python :: 3.9
Classifier: Programming Language :: Python :: 3.10
Requires-Python: ~=3.4
Requires-Dist: seven-framework (>=1.1.51)
